rich_run/__init__.py
rich_run/banner.py
rich_run/main.py
rich_run-0.1.2.dist-info/licenses/LICENSE
rich_run-0.1.2.dist-info/METADATA
rich_run-0.1.2.dist-info/WHEEL
rich_run-0.1.2.dist-info/entry_points.txt
rich_run-0.1.2.dist-info/top_level.txt
rich_run-0.1.2.dist-info/RECORD
