Metadata-Version: 2.4
Name: rich-run
Version: 0.1.2
Summary: A command runner with rich formatting
Author-email: Anke Tang <tang.anke@foxmail.com>
License: MIT
Project-URL: Homepage, https://github.com/tanganke/rich-run
Project-URL: Repository, https://github.com/tanganke/rich-run
Requires-Python: >=3.8
License-File: LICENSE
Requires-Dist: rich-cli
Dynamic: license-file
